Workbook
Name CDM_Paths: '1. CDM Schema Registry'!$A$3:$A$200
Name BDE_Names: '2. CDM to BDE Mapping'!$B$3:$B$200

Sheet How to Use
B2: WCDM Workflow Template
B3: Whole Customer Data Model | Schema, Mapping, and Governance
B5: About This Template
B6: This template manages the three core WCDM mappings: CDM Path to BDE, BDE to SOR, and BDE to Business Requirement. CDM Path and BDE Name are the natural keys that connect all tabs. There are no separate ID columns. The blue-highlighted columns on each tab are auto-calculated using XLOOKUP and pull cross-tab context so you never have to look up related data manually. Requires Excel 2019 or Microsoft 365 for the XLOOKUP formulas.
B8: Tab Guide
B9: Tab 1: CDM Schema Registry | C9: The single source of truth for every CDM leaf path. Register new paths here first before adding any mappings. CDM Path is the primary key that all other tabs reference.
B10: Tab 2: CDM to BDE Mapping | C10: Links each CDM path to its Business Data Element. The auto-column on this tab pulls Data Type directly from Tab 1 so you can see the schema context without switching tabs.
B11: Tab 3: BDE to SOR Mapping | C11: Maps each BDE to the source systems and product types that supply it (1-to-many). The auto-column pulls the BDE Definition from Tab 2 for quick reference while you fill in transformation logic.
B12: Tab 4: Business Requirements | C12: Where consumer requirements enter the process. Link each requirement to the BDEs it depends on. The auto-column pulls the CDM Path from Tab 2. Flag blocked requirements with a Gap Type to drive change requests.
B13: Tab 5: Change Request Log | C13: Governance record for all schema evolution. Every proposed addition, deprecation, or SOR onboarding is tracked here with a business outcome and an approval status. Once approved, go back and update Tabs 1, 2, and 3.
B15: How the Tabs Connect
B16: Join Key | C16: Which Tabs | D16: How It Works
B17: CDM Path | C17: Tab 1 (Schema Registry) and Tab 2 (CDM to BDE Mapping) | D17: Tab 2 col A must match a CDM Path from Tab 1. The CDM Path dropdown on Tab 2 is pre-loaded from Tab 1. The auto-column on Tab 2 pulls Data Type from Tab 1 via CDM Path.
B18: BDE Name | C18: Tab 2 (CDM to BDE Mapping) and Tabs 3, 4 | D18: Tab 3 col A and Tab 4 col D reference BDE Names from Tab 2. The BDE Name dropdown on those tabs is pre-loaded from Tab 2. Auto-columns pull BDE Definition (Tab 3) and CDM Path (Tab 4) from Tab 2 via BDE Name.
B19: Blocked Status | C19: Tab 4 (Business Requirements) and Tab 5 (Change Request Log) | D19: When a row on Tab 4 shows Blocked - Source Gap or Blocked - Schema Gap, that is the trigger to open Tab 5. The Proposed CDM Path on Tab 5 should correspond to the gap identified on Tab 4.
B20: Approval | C20: Tab 5 (Change Request Log) and Tabs 1, 2, 3 | D20: Once a request on Tab 5 reaches Approved status, return to Tabs 1, 2, and 3 to register the new CDM path, add the BDE mapping, and add the SOR mapping.
B22: Requirement Intake Workflow
B23: Note: The tabs are organized by data type for maintenance. The workflow below does not follow tab order. Each step tells you exactly which tab to open.
B24: Step 1 | C24: A consumer brings a use case. Open TAB 4 (Business Requirements). Enter the requirement, the consumer or stakeholder, and the business outcome it needs to achieve. Leave BDE Name blank until you complete the next step.
B25: Step 2 | C25: Check whether the required concept already exists in the schema. Open TAB 2 (CDM to BDE Mapping). Search the BDE Name column. If a matching BDE exists, copy it into the BDE Name field on Tab 4. The CDM Path auto-column will populate automatically.
B26: Step 3 | C26: Check whether the source data is already onboarded. Open TAB 3 (BDE to SOR Mapping). Filter by the BDE Name. If the required product type and SOR combination already has a mapping row, no change request is needed. Set the Tab 4 status to Active.
B27: Step 4 | C27: If something is missing, open TAB 5 (Change Request Log). If the BDE does not exist in Tab 2, select Request Type: New Attribute. If the BDE exists but the SOR or product type is not in Tab 3, select Request Type: New SOR or New Product Type. Complete the business outcome and schema fields, then set status to Proposed.
B28: Step 5 | C28: Once a request on Tab 5 reaches Approved status, update the registries. Add the new CDM path to TAB 1 (CDM Schema Registry), add the BDE mapping to TAB 2 (CDM to BDE Mapping), and add the SOR mapping to TAB 3 (BDE to SOR Mapping). Return to Tab 4 and clear the Gap Type and update the status to Active.
B30: Status Color Legend
B31: Active | C31: Current and in use.
B32: Deprecated | C32: Replaced by a newer path or mapping. Retained for traceability.
B33: Proposed | C33: A change request has been submitted and is awaiting review.
B34: Under Review | C34: Actively being assessed by the governance team.
B35: Approved | C35: Approved and ready for implementation.
B36: Rejected | C36: Declined. See Decision Notes for context.
B38: Auto-columns (light blue headers): These columns are populated by XLOOKUP formulas. Do not edit them directly. They update when you enter or change a key value in the same row.

Sheet 1. CDM Schema Registry
A1: CDM Schema Registry | Tab 1
A2: CDM Path | B2: Domain | C2: Data Type | D2: Cardinality | E2: Status | F2: Business Description | G2: Owner Team | H2: Schema Version | I2: Deprecation Notes
A3: customer.identity.fullName | B3: Customer | C3: String | D3: 1 | E3: Active | F3: Full legal name of the customer as recorded in the source system. | G3: Data Governance | H3: 1.0
A4: customer.identity.dateOfBirth | B4: Customer | C4: Date | D4: 0..1 | E4: Active | F4: Customer date of birth in ISO 8601 format (YYYY-MM-DD). | G4: Data Governance | H4: 1.0
A5: customer.contact.emailAddress | B5: Customer | C5: String | D5: 0..N | E5: Active | F5: All registered email addresses for the customer. | G5: Data Governance | H5: 1.0
A6: customer.employment.annualIncomeAmount | B6: Customer | C6: Decimal | D6: 0..1 | E6: Active | F6: Gross annual income of the customer as declared or verified at origination, in base currency. | G6: Finance Data | H6: 1.1
A7: account.balance.currentAmount | B7: Account | C7: Decimal | D7: 1 | E7: Active | F7: Current balance of the account in its base currency at a point in time. | G7: Finance Data | H7: 1.0
A8: account.balance.currency | B8: Account | C8: String | D8: 1 | E8: Active | F8: ISO 4217 three-character currency code for the account balance. | G8: Finance Data | H8: 1.0
A9: account.status.code | B9: Account | C9: String | D9: 1 | E9: Active | F9: Operational status of the account (e.g., Active, Closed, Suspended). | G9: Operations | H9: 1.0
A10: account.product.typeCode | B10: Account | C10: String | D10: 1 | E10: Active | F10: Product classification code assigned to this account in the WCDM product taxonomy. | G10: Product | H10: 1.0
A11: transaction.amount.value | B11: Transaction | C11: Decimal | D11: 1 | E11: Active | F11: Monetary value of the transaction before any fees or adjustments. | G11: Finance Data | H11: 1.0
A12: transaction.date.effectiveDate | B12: Transaction | C12: Date | D12: 1 | E12: Active | F12: Business date on which the transaction takes effect for accounting purposes. | G12: Finance Data | H12: 1.0
A13: customer.identity.legalEntityName | B13: Customer | C13: String | D13: 0..1 | E13: Deprecated | F13: Legal entity name superseded by customer.identity.fullName in v1.1. | G13: Data Governance | H13: 1.0 | I13: Replaced by customer.identity.fullName as of v1.1. Retained for traceability only.

Sheet 2. CDM to BDE Mapping
A1: CDM Path to BDE Mapping | Tab 2
A2: CDM Path | B2: BDE Name | C2: BDE Definition | D2: Business Owner | E2: Mapping Status | F2: Deprecation Reason | G2: Notes | H2: Data Type (auto)
A3: customer.identity.fullName | B3: Customer Full Name | C3: The complete legal name of an individual as provided to and verified by the institution. | D3: Data Governance | E3: Active | H3: =IFERROR(XLOOKUP(A3,'1. CDM Schema Registry'!$A:$A,'1. CDM Schema Registry'!$C:$C,""),"")
A4: customer.identity.dateOfBirth | B4: Customer Date of Birth | C4: The date on which the customer was born. Used for identity verification, eligibility, and regulatory reporting. | D4: Data Governance | E4: Active | H4: =IFERROR(XLOOKUP(A4,'1. CDM Schema Registry'!$A:$A,'1. CDM Schema Registry'!$C:$C,""),"")
A5: customer.contact.emailAddress | B5: Customer Email Address | C5: A valid electronic mail address associated with the customer for communication and notification. | D5: Data Governance | E5: Active | H5: =IFERROR(XLOOKUP(A5,'1. CDM Schema Registry'!$A:$A,'1. CDM Schema Registry'!$C:$C,""),"")
A6: customer.employment.annualIncomeAmount | B6: Customer Annual Income Amount | C6: The gross annual income of a customer as declared or verified at origination, expressed in base currency. | D6: Finance Data | E6: Active | G6: Added in v1.1 to support credit risk use cases. | H6: =IFERROR(XLOOKUP(A6,'1. CDM Schema Registry'!$A:$A,'1. CDM Schema Registry'!$C:$C,""),"")
A7: account.balance.currentAmount | B7: Account Current Balance | C7: The net monetary value held in an account at a given point in time, expressed in the account base currency. | D7: Finance Data | E7: Active | H7: =IFERROR(XLOOKUP(A7,'1. CDM Schema Registry'!$A:$A,'1. CDM Schema Registry'!$C:$C,""),"")
A8: account.balance.currency | B8: Account Currency Code | C8: The ISO 4217 code representing the denomination currency of the account balance. | D8: Finance Data | E8: Active | H8: =IFERROR(XLOOKUP(A8,'1. CDM Schema Registry'!$A:$A,'1. CDM Schema Registry'!$C:$C,""),"")
A9: account.status.code | B9: Account Status | C9: The current operational lifecycle state of an account, governing what actions may be performed on it. | D9: Operations | E9: Active | H9: =IFERROR(XLOOKUP(A9,'1. CDM Schema Registry'!$A:$A,'1. CDM Schema Registry'!$C:$C,""),"")
A10: account.product.typeCode | B10: Product Type Code | C10: A standardized code classifying the product type associated with an account in the WCDM product taxonomy. | D10: Product | E10: Active | H10: =IFERROR(XLOOKUP(A10,'1. CDM Schema Registry'!$A:$A,'1. CDM Schema Registry'!$C:$C,""),"")
A11: transaction.amount.value | B11: Transaction Amount | C11: The gross monetary value of a financial transaction prior to fee or adjustment application. | D11: Finance Data | E11: Active | H11: =IFERROR(XLOOKUP(A11,'1. CDM Schema Registry'!$A:$A,'1. CDM Schema Registry'!$C:$C,""),"")
A12: transaction.date.effectiveDate | B12: Transaction Effective Date | C12: The business calendar date on which a transaction is recognized as having occurred for accounting purposes. | D12: Finance Data | E12: Active | H12: =IFERROR(XLOOKUP(A12,'1. CDM Schema Registry'!$A:$A,'1. CDM Schema Registry'!$C:$C,""),"")
A13: customer.identity.legalEntityName | B13: Customer Full Name | C13: The complete legal name of an individual as provided to and verified by the institution. | D13: Data Governance | E13: Deprecated | F13: Superseded by customer.identity.fullName in v1.1. BDE unchanged; this CDM path mapping is deprecated. | H13: =IFERROR(XLOOKUP(A13,'1. CDM Schema Registry'!$A:$A,'1. CDM Schema Registry'!$C:$C,""),"")
H14: =IFERROR(XLOOKUP(A14,'1. CDM Schema Registry'!$A:$A,'1. CDM Schema Registry'!$C:$C,""),"")
H15: =IFERROR(XLOOKUP(A15,'1. CDM Schema Registry'!$A:$A,'1. CDM Schema Registry'!$C:$C,""),"")
H16: =IFERROR(XLOOKUP(A16,'1. CDM Schema Registry'!$A:$A,'1. CDM Schema Registry'!$C:$C,""),"")
H17: =IFERROR(XLOOKUP(A17,'1. CDM Schema Registry'!$A:$A,'1. CDM Schema Registry'!$C:$C,""),"")
H18: =IFERROR(XLOOKUP(A18,'1. CDM Schema Registry'!$A:$A,'1. CDM Schema Registry'!$C:$C,""),"")
H19: =IFERROR(XLOOKUP(A19,'1. CDM Schema Registry'!$A:$A,'1. CDM Schema Registry'!$C:$C,""),"")
H20: =IFERROR(XLOOKUP(A20,'1. CDM Schema Registry'!$A:$A,'1. CDM Schema Registry'!$C:$C,""),"")
H21: =IFERROR(XLOOKUP(A21,'1. CDM Schema Registry'!$A:$A,'1. CDM Schema Registry'!$C:$C,""),"")
H22: =IFERROR(XLOOKUP(A22,'1. CDM Schema Registry'!$A:$A,'1. CDM Schema Registry'!$C:$C,""),"")
H23: =IFERROR(XLOOKUP(A23,'1. CDM Schema Registry'!$A:$A,'1. CDM Schema Registry'!$C:$C,""),"")
H24: =IFERROR(XLOOKUP(A24,'1. CDM Schema Registry'!$A:$A,'1. CDM Schema Registry'!$C:$C,""),"")
H25: =IFERROR(XLOOKUP(A25,'1. CDM Schema Registry'!$A:$A,'1. CDM Schema Registry'!$C:$C,""),"")
... H200: =IFERROR(XLOOKUP(A200,'1. CDM Schema Registry'!$A:$A,'1. CDM Schema Registry'!$C:$C,""),"")

Sheet 3. BDE to SOR Mapping
A1: BDE to System of Record (SOR) Mapping | Tab 3
A2: BDE Name | B2: System of Record (SOR) | C2: Product Type | D2: Source Attribute | E2: Transformation Logic | F2: Mapping Type | G2: Status | H2: Notes | I2: BDE Definition (auto)
A3: Customer Full Name | B3: CRM_SYSTEM | C3: All Products | D3: CUST_FULL_NAME | E3: Trim whitespace. Apply title-case. | F3: Direct | G3: Active | I3: =IFERROR(XLOOKUP(A3,'2. CDM to BDE Mapping'!$B:$B,'2. CDM to BDE Mapping'!$C:$C,""),"")
A4: Customer Full Name | B4: CORE_BANKING | C4: Deposit | D4: FIRST_NME + LAST_NME | E4: Concatenate FIRST_NME + ' ' + LAST_NME. Trim. Apply title-case. | F4: Transformed | G4: Active | H4: Core banking stores first and last name in separate fields. | I4: =IFERROR(XLOOKUP(A4,'2. CDM to BDE Mapping'!$B:$B,'2. CDM to BDE Mapping'!$C:$C,""),"")
A5: Customer Date of Birth | B5: CRM_SYSTEM | C5: All Products | D5: DATE_OF_BIRTH | E5: Convert from MM/DD/YYYY to ISO 8601 YYYY-MM-DD. | F5: Transformed | G5: Active | I5: =IFERROR(XLOOKUP(A5,'2. CDM to BDE Mapping'!$B:$B,'2. CDM to BDE Mapping'!$C:$C,""),"")
A6: Customer Email Address | B6: CRM_SYSTEM | C6: All Products | D6: EMAIL_ADDR | E6: Lowercase. Validate against RFC 5321 format. | F6: Direct | G6: Active | I6: =IFERROR(XLOOKUP(A6,'2. CDM to BDE Mapping'!$B:$B,'2. CDM to BDE Mapping'!$C:$C,""),"")
A7: Customer Annual Income Amount | B7: CRM_SYSTEM | C7: All Products | D7: ANNUAL_INCOME | E7: Cast to Decimal(18,6). Null treated as not provided. | F7: Direct | G7: Active | I7: =IFERROR(XLOOKUP(A7,'2. CDM to BDE Mapping'!$B:$B,'2. CDM to BDE Mapping'!$C:$C,""),"")
A8: Account Current Balance | B8: CORE_BANKING | C8: Deposit | D8: CURR_BAL_AMT | E8: Cast to Decimal(18,6). Null handled as 0.00. | F8: Direct | G8: Active | I8: =IFERROR(XLOOKUP(A8,'2. CDM to BDE Mapping'!$B:$B,'2. CDM to BDE Mapping'!$C:$C,""),"")
A9: Account Current Balance | B9: PORTFOLIO_MGMT | C9: Investment | D9: PORTFOLIO_VALUE | E9: Sum POSITION_MKT_VALUE across all holdings for the account. Point-in-time snapshot. | F9: Derived | G9: Active | H9: Derived from multiple position-level records. | I9: =IFERROR(XLOOKUP(A9,'2. CDM to BDE Mapping'!$B:$B,'2. CDM to BDE Mapping'!$C:$C,""),"")
A10: Account Currency Code | B10: CORE_BANKING | C10: Deposit | D10: CURRENCY_CD | E10: Validate against ISO 4217 reference table. | F10: Direct | G10: Active | I10: =IFERROR(XLOOKUP(A10,'2. CDM to BDE Mapping'!$B:$B,'2. CDM to BDE Mapping'!$C:$C,""),"")
A11: Account Currency Code | B11: PORTFOLIO_MGMT | C11: Investment | D11: BASE_CCY | E11: Validate against ISO 4217 reference table. | F11: Direct | G11: Active | I11: =IFERROR(XLOOKUP(A11,'2. CDM to BDE Mapping'!$B:$B,'2. CDM to BDE Mapping'!$C:$C,""),"")
A12: Account Status | B12: CORE_BANKING | C12: All Products | D12: ACCT_STAT_CD | E12: Apply lookup: A = Active, C = Closed, S = Suspended. | F12: Conditional | G12: Active | H12: Source uses proprietary single-character codes. | I12: =IFERROR(XLOOKUP(A12,'2. CDM to BDE Mapping'!$B:$B,'2. CDM to BDE Mapping'!$C:$C,""),"")
A13: Product Type Code | B13: CORE_BANKING | C13: All Products | D13: PROD_TYPE_CD | E13: Map to WCDM product taxonomy lookup table. | F13: Conditional | G13: Active | H13: Lookup table maintained by Product team. | I13: =IFERROR(XLOOKUP(A13,'2. CDM to BDE Mapping'!$B:$B,'2. CDM to BDE Mapping'!$C:$C,""),"")
A14: Transaction Amount | B14: CORE_BANKING | C14: Deposit | D14: TXN_AMT | E14: Take absolute value. Credit/debit direction handled by a separate BDE. | F14: Direct | G14: Active | I14: =IFERROR(XLOOKUP(A14,'2. CDM to BDE Mapping'!$B:$B,'2. CDM to BDE Mapping'!$C:$C,""),"")
A15: Transaction Amount | B15: TRADE_SYSTEM | C15: Investment | D15: TRADE_GROSS_AMT | E15: Cast to Decimal(18,6). Exclude accrued interest. | F15: Transformed | G15: Active | I15: =IFERROR(XLOOKUP(A15,'2. CDM to BDE Mapping'!$B:$B,'2. CDM to BDE Mapping'!$C:$C,""),"")
A16: Transaction Effective Date | B16: CORE_BANKING | C16: Deposit | D16: VALUE_DT | E16: Convert from YYYYMMDD integer format to ISO 8601 Date. | F16: Transformed | G16: Active | I16: =IFERROR(XLOOKUP(A16,'2. CDM to BDE Mapping'!$B:$B,'2. CDM to BDE Mapping'!$C:$C,""),"")
A17: Transaction Effective Date | B17: TRADE_SYSTEM | C17: Investment | D17: SETTLEMENT_DATE | E17: Convert from MM/DD/YYYY to ISO 8601 YYYY-MM-DD. | F17: Transformed | G17: Active | I17: =IFERROR(XLOOKUP(A17,'2. CDM to BDE Mapping'!$B:$B,'2. CDM to BDE Mapping'!$C:$C,""),"")
I18: =IFERROR(XLOOKUP(A18,'2. CDM to BDE Mapping'!$B:$B,'2. CDM to BDE Mapping'!$C:$C,""),"")
I19: =IFERROR(XLOOKUP(A19,'2. CDM to BDE Mapping'!$B:$B,'2. CDM to BDE Mapping'!$C:$C,""),"")
I20: =IFERROR(XLOOKUP(A20,'2. CDM to BDE Mapping'!$B:$B,'2. CDM to BDE Mapping'!$C:$C,""),"")
I21: =IFERROR(XLOOKUP(A21,'2. CDM to BDE Mapping'!$B:$B,'2. CDM to BDE Mapping'!$C:$C,""),"")
I22: =IFERROR(XLOOKUP(A22,'2. CDM to BDE Mapping'!$B:$B,'2. CDM to BDE Mapping'!$C:$C,""),"")
I23: =IFERROR(XLOOKUP(A23,'2. CDM to BDE Mapping'!$B:$B,'2. CDM to BDE Mapping'!$C:$C,""),"")
I24: =IFERROR(XLOOKUP(A24,'2. CDM to BDE Mapping'!$B:$B,'2. CDM to BDE Mapping'!$C:$C,""),"")
I25: =IFERROR(XLOOKUP(A25,'2. CDM to BDE Mapping'!$B:$B,'2. CDM to BDE Mapping'!$C:$C,""),"")
I26: =IFERROR(XLOOKUP(A26,'2. CDM to BDE Mapping'!$B:$B,'2. CDM to BDE Mapping'!$C:$C,""),"")
I27: =IFERROR(XLOOKUP(A27,'2. CDM to BDE Mapping'!$B:$B,'2. CDM to BDE Mapping'!$C:$C,""),"")
I28: =IFERROR(XLOOKUP(A28,'2. CDM to BDE Mapping'!$B:$B,'2. CDM to BDE Mapping'!$C:$C,""),"")
I29: =IFERROR(XLOOKUP(A29,'2. CDM to BDE Mapping'!$B:$B,'2. CDM to BDE Mapping'!$C:$C,""),"")
... I200: =IFERROR(XLOOKUP(A200,'2. CDM to BDE Mapping'!$B:$B,'2. CDM to BDE Mapping'!$C:$C,""),"")

Sheet 4. Business Requirements
A1: BDE to Business Requirements Mapping | Tab 4
A2: Business Requirement | B2: Consumer / Stakeholder | C2: Business Outcome | D2: BDE Name | E2: Priority | F2: Status | G2: Gap Type | H2: Notes | I2: CDM Path (auto)
A3: KYC Identity Verification | B3: Compliance | C3: Satisfy regulatory KYC obligation by confirming customer identity at onboarding. | D3: Customer Full Name | E3: High | F3: Active | G3: None | H3: Drives AML and onboarding screening. | I3: =IFERROR(XLOOKUP(D3,'2. CDM to BDE Mapping'!$B:$B,'2. CDM to BDE Mapping'!$A:$A,""),"")
A4: KYC Identity Verification | B4: Compliance | C4: Satisfy regulatory KYC obligation by confirming customer identity at onboarding. | D4: Customer Date of Birth | E4: High | F4: Active | G4: None | H4: Required for age-based and sanctions checks. | I4: =IFERROR(XLOOKUP(D4,'2. CDM to BDE Mapping'!$B:$B,'2. CDM to BDE Mapping'!$A:$A,""),"")
A5: Customer Communication Segmentation | B5: Marketing | C5: Identify customers with a verified email address for digital campaign targeting. | D5: Customer Email Address | E5: Medium | F5: Active | G5: None | H5: Linked to consent management records. | I5: =IFERROR(XLOOKUP(D5,'2. CDM to BDE Mapping'!$B:$B,'2. CDM to BDE Mapping'!$A:$A,""),"")
A6: 360 Account Balance Dashboard | B6: Wealth Advisory | C6: Display current balance across all account types in a single adviser view. | D6: Account Current Balance | E6: High | F6: Active | G6: None | H6: Requires Deposit and Investment SOR coverage. | I6: =IFERROR(XLOOKUP(D6,'2. CDM to BDE Mapping'!$B:$B,'2. CDM to BDE Mapping'!$A:$A,""),"")
A7: 360 Account Balance Dashboard | B7: Wealth Advisory | C7: Display current balance across all account types in a single adviser view. | D7: Account Currency Code | E7: High | F7: Active | G7: None | I7: =IFERROR(XLOOKUP(D7,'2. CDM to BDE Mapping'!$B:$B,'2. CDM to BDE Mapping'!$A:$A,""),"")
A8: AML Transaction Monitoring | B8: Compliance | C8: Flag high-value or unusual transactions for AML review within the required reporting window. | D8: Transaction Amount | E8: High | F8: Active | G8: None | H8: Thresholds defined in compliance policy. | I8: =IFERROR(XLOOKUP(D8,'2. CDM to BDE Mapping'!$B:$B,'2. CDM to BDE Mapping'!$A:$A,""),"")
A9: AML Transaction Monitoring | B9: Compliance | C9: Flag high-value or unusual transactions for AML review within the required reporting window. | D9: Transaction Effective Date | E9: High | F9: Active | G9: None | I9: =IFERROR(XLOOKUP(D9,'2. CDM to BDE Mapping'!$B:$B,'2. CDM to BDE Mapping'!$A:$A,""),"")
A10: Product Performance Reporting | B10: Product Analytics | C10: Calculate revenue and volume metrics per product type across all active SORs. | D10: Product Type Code | E10: High | F10: Active | G10: None | H10: Requires consistent product taxonomy across all SORs. | I10: =IFERROR(XLOOKUP(D10,'2. CDM to BDE Mapping'!$B:$B,'2. CDM to BDE Mapping'!$A:$A,""),"")
A11: Mortgage Origination Risk Scoring | B11: Credit Risk | C11: Score applicants for mortgage origination using verified income and employment history. | D11: Customer Annual Income Amount | E11: High | F11: Active | G11: None | H11: Income attribute added in v1.1 following approved change request. | I11: =IFERROR(XLOOKUP(D11,'2. CDM to BDE Mapping'!$B:$B,'2. CDM to BDE Mapping'!$A:$A,""),"")
A12: Trust Account Regulatory Reporting | B12: Legal | C12: Produce required regulatory reports for accounts held in trust on behalf of legal entities. | D12: Account Status | E12: Medium | F12: Blocked - Source Gap | G12: Source Onboarding Needed | H12: Trust administration system not yet onboarded. Change request open on Tab 5. | I12: =IFERROR(XLOOKUP(D12,'2. CDM to BDE Mapping'!$B:$B,'2. CDM to BDE Mapping'!$A:$A,""),"")
A13: Retirement Account Eligibility Check | B13: Operations | C13: Determine whether a customer meets age-based eligibility rules for retirement account products. | D13: Customer Date of Birth | E13: Medium | F13: Active | G13: None | I13: =IFERROR(XLOOKUP(D13,'2. CDM to BDE Mapping'!$B:$B,'2. CDM to BDE Mapping'!$A:$A,""),"")
I14: =IFERROR(XLOOKUP(D14,'2. CDM to BDE Mapping'!$B:$B,'2. CDM to BDE Mapping'!$A:$A,""),"")
I15: =IFERROR(XLOOKUP(D15,'2. CDM to BDE Mapping'!$B:$B,'2. CDM to BDE Mapping'!$A:$A,""),"")
I16: =IFERROR(XLOOKUP(D16,'2. CDM to BDE Mapping'!$B:$B,'2. CDM to BDE Mapping'!$A:$A,""),"")
I17: =IFERROR(XLOOKUP(D17,'2. CDM to BDE Mapping'!$B:$B,'2. CDM to BDE Mapping'!$A:$A,""),"")
I18: =IFERROR(XLOOKUP(D18,'2. CDM to BDE Mapping'!$B:$B,'2. CDM to BDE Mapping'!$A:$A,""),"")
I19: =IFERROR(XLOOKUP(D19,'2. CDM to BDE Mapping'!$B:$B,'2. CDM to BDE Mapping'!$A:$A,""),"")
I20: =IFERROR(XLOOKUP(D20,'2. CDM to BDE Mapping'!$B:$B,'2. CDM to BDE Mapping'!$A:$A,""),"")
I21: =IFERROR(XLOOKUP(D21,'2. CDM to BDE Mapping'!$B:$B,'2. CDM to BDE Mapping'!$A:$A,""),"")
I22: =IFERROR(XLOOKUP(D22,'2. CDM to BDE Mapping'!$B:$B,'2. CDM to BDE Mapping'!$A:$A,""),"")
I23: =IFERROR(XLOOKUP(D23,'2. CDM to BDE Mapping'!$B:$B,'2. CDM to BDE Mapping'!$A:$A,""),"")
I24: =IFERROR(XLOOKUP(D24,'2. CDM to BDE Mapping'!$B:$B,'2. CDM to BDE Mapping'!$A:$A,""),"")
I25: =IFERROR(XLOOKUP(D25,'2. CDM to BDE Mapping'!$B:$B,'2. CDM to BDE Mapping'!$A:$A,""),"")
... I200: =IFERROR(XLOOKUP(D200,'2. CDM to BDE Mapping'!$B:$B,'2. CDM to BDE Mapping'!$A:$A,""),"")

Sheet 5. Change Request Log
A1: Schema Change Request Log | Tab 5
A2: Proposed CDM Path | B2: Request Type | C2: Consumer / Stakeholder | D2: Business Outcome Blocked | E2: Existing Schema Sufficient? | F2: Resolution Type | G2: BDE Name | H2: BDE Definition | I2: Data Type | J2: Cardinality | K2: Reusable Across Products? | L2: Proposed Owner | M2: Request Status | N2: Approval Date | O2: Decision Notes
A3: customer.employment.annualIncomeAmount | B3: New Attribute | C3: Credit Risk | D3: Mortgage origination risk scoring cannot proceed without annual income. The scoring model is blocked at current schema coverage. | E3: No | F3: Schema Change | G3: Customer Annual Income Amount | H3: The gross annual income of a customer as declared or verified at origination, expressed in base currency. | I3: Decimal | J3: 0..1 | K3: Yes | L3: Finance Data | M3: Approved | N3: 2026-05-14 | O3: Approved by Data Governance Board. Reusable for credit, KYC, and product eligibility. Added to Tab 1 and Tab 2 as v1.1.
A4: account.trust.adminSystem | B4: New SOR | C4: Legal | D4: Trust account regulatory reporting cannot be produced because the trust administration system has not been onboarded as a SOR. | E4: Yes | F4: Source Onboarding | L4: Operations | M4: Under Review | O4: WCDM schema already contains the required elements. Priority is SOR onboarding. Legal team to confirm data owner and ingestion schedule.
A5: customer.risk.creditScoreBand | B5: New Attribute | C5: Retail Banking | D5: Personalized product recommendations require a credit risk band. No adequate approximation exists in the current schema. | E5: No | F5: Schema Change | G5: Customer Credit Score Band | H5: A standardized tier (e.g., A, B, C, D) representing the customer credit risk classification as assessed by the institution. | I5: String | J5: 0..1 | K5: Yes | L5: Risk | M5: Proposed | O5: Under initial governance review. Confirm regulatory sensitivity and data privacy classification before approving.
A6: customer.identity.legalEntityName | B6: Deprecation | C6: Data Governance | D6: customer.identity.legalEntityName is redundant following consolidation into customer.identity.fullName in v1.1. | E6: Yes | F6: No Action Required | G6: Customer Full Name | L6: Data Governance | M6: Approved | N6: 2026-03-01 | O6: Path deprecated in v1.1. Retained in Tab 1 for traceability. All downstream consumers confirmed migrated to customer.identity.fullName.
