Workbook

Sheet Field Map
A1: Mapping 1 of 3 — WCDM Leaf → BDE (1:1). One row per WCDM leaf path. This is the schema registry. Sheets 2, 3, and 4 all reference column A. | White = type Gold = select from list Blue = auto-filled
A2: WCDM Leaf + BDE Definition | G2: Governance
A3: WCDM Leaf Path | B3: BDE Name | C3: Business Definition | D3: Data Type | E3: Cardinality | F3: Mapping Status | G3: Extension Decision | H3: Business Outcome | I3: Owner
A4: account.position.marketValue.amount | B4: Market Value | C4: Fair market value of a financial position as of the reporting date. | D4: decimal | E4: 0..1 | F4: Active | G4: Schema Extension | H4: Required for daily P&L reporting and front office valuation across equity and fixed income. | I4: Data Architecture
A5: account.identifier.accountNumber | B5: Account Number | C5: Unique identifier assigned to a client account by the system of record. | D5: string | E5: 1..1 | F5: Active | G5: Source Expansion | H5: Required for regulatory capital calculation and client-level reporting. | I5: Data Architecture

Sheet Source Map
A1: Mapping 2 of 3 — BDE → SOR/Product (1:Many). One row per WCDM path + SOR combination. Same path appears twice if it has two sources. BDE Name auto-fills — do not type it here. | White = type Gold = select from list Blue = auto-filled
A2: From Field Map (auto) | C2: Source Detail | H2: Quality
A3: WCDM Leaf Path | B3: BDE Name | C3: System of Record | D3: Product Type | E3: Source Attribute | F3: Transform / Normalization Logic | G3: Precedence Rule | H3: Gap Classification | I3: Notes
A4: account.position.marketValue.amount | B4: =IFERROR(VLOOKUP(A4,'Field Map'!$A:$Z,2,0),"") -> Market Value | C4: Bloomberg | D4: Equity | E4: CURRENT_VALUE | F4: Numeric direct map. Divide by 100 if source delivers in pence. | G4: Bloomberg takes precedence when both SORs available. | H4: Direct Map
A5: account.position.marketValue.amount | B5: =IFERROR(VLOOKUP(A5,'Field Map'!$A:$Z,2,0),"") -> Market Value | C5: Calypso | D5: Fixed Income | E5: MKT_VAL | F5: Numeric direct map. | G5: Bloomberg takes precedence when both SORs available. | H5: Direct Map
A6: account.identifier.accountNumber | B6: =IFERROR(VLOOKUP(A6,'Field Map'!$A:$Z,2,0),"") -> Account Number | C6: Bloomberg | D6: All Products | E6: ACCT_ID | F6: String direct map. | G6: Single source — no precedence rule needed. | H6: Direct Map
B7: =IFERROR(VLOOKUP(A7,'Field Map'!$A:$Z,2,0),"")
B8: =IFERROR(VLOOKUP(A8,'Field Map'!$A:$Z,2,0),"")
B9: =IFERROR(VLOOKUP(A9,'Field Map'!$A:$Z,2,0),"")
B10: =IFERROR(VLOOKUP(A10,'Field Map'!$A:$Z,2,0),"")
B11: =IFERROR(VLOOKUP(A11,'Field Map'!$A:$Z,2,0),"")
B12: =IFERROR(VLOOKUP(A12,'Field Map'!$A:$Z,2,0),"")
B13: =IFERROR(VLOOKUP(A13,'Field Map'!$A:$Z,2,0),"")
B14: =IFERROR(VLOOKUP(A14,'Field Map'!$A:$Z,2,0),"")
B15: =IFERROR(VLOOKUP(A15,'Field Map'!$A:$Z,2,0),"")
B16: =IFERROR(VLOOKUP(A16,'Field Map'!$A:$Z,2,0),"")
B17: =IFERROR(VLOOKUP(A17,'Field Map'!$A:$Z,2,0),"")
B18: =IFERROR(VLOOKUP(A18,'Field Map'!$A:$Z,2,0),"")
... B123: =IFERROR(VLOOKUP(A123,'Field Map'!$A:$Z,2,0),"")

Sheet Requirements
A1: Mapping 3 of 3 — BDE → Business Requirements (Many:Many). One row per path + requirement pair. Same path on two rows = two requirements it serves. Same requirement on two rows = two paths that satisfy it. | White = type Gold = select from list Blue = auto-filled
A2: From Field Map (auto) | C2: Business Requirement
A3: WCDM Leaf Path | B3: BDE Name | C3: Requirement ID | D3: Requirement | E3: Consumer Team | F3: Priority | G3: Notes
A4: account.position.marketValue.amount | B4: =IFERROR(VLOOKUP(A4,'Field Map'!$A:$Z,2,0),"") -> Market Value | C4: BR-001 | D4: Daily P&L reporting requires accurate market value for all open positions. | E4: Risk Analytics | F4: High | G4: Primary requirement driving the Schema Extension decision.
A5: account.position.marketValue.amount | B5: =IFERROR(VLOOKUP(A5,'Field Map'!$A:$Z,2,0),"") -> Market Value | C5: BR-002 | D5: Front office valuation dashboard requires intraday position pricing. | E5: Front Office | F5: High | G5: Same path satisfies a second consumer.
A6: account.identifier.accountNumber | B6: =IFERROR(VLOOKUP(A6,'Field Map'!$A:$Z,2,0),"") -> Account Number | C6: BR-003 | D6: Regulatory capital calculation requires account-level position data. | E6: Regulatory Reporting | F6: High
A7: account.position.marketValue.amount | B7: =IFERROR(VLOOKUP(A7,'Field Map'!$A:$Z,2,0),"") -> Market Value | C7: BR-003 | D7: Regulatory capital calculation requires account-level position data. | E7: Regulatory Reporting | F7: High | G7: BR-003 is served by two BDEs — this row and the row above complete the Many:Many.
B8: =IFERROR(VLOOKUP(A8,'Field Map'!$A:$Z,2,0),"")
B9: =IFERROR(VLOOKUP(A9,'Field Map'!$A:$Z,2,0),"")
B10: =IFERROR(VLOOKUP(A10,'Field Map'!$A:$Z,2,0),"")
B11: =IFERROR(VLOOKUP(A11,'Field Map'!$A:$Z,2,0),"")
B12: =IFERROR(VLOOKUP(A12,'Field Map'!$A:$Z,2,0),"")
B13: =IFERROR(VLOOKUP(A13,'Field Map'!$A:$Z,2,0),"")
B14: =IFERROR(VLOOKUP(A14,'Field Map'!$A:$Z,2,0),"")
B15: =IFERROR(VLOOKUP(A15,'Field Map'!$A:$Z,2,0),"")
B16: =IFERROR(VLOOKUP(A16,'Field Map'!$A:$Z,2,0),"")
B17: =IFERROR(VLOOKUP(A17,'Field Map'!$A:$Z,2,0),"")
B18: =IFERROR(VLOOKUP(A18,'Field Map'!$A:$Z,2,0),"")
B19: =IFERROR(VLOOKUP(A19,'Field Map'!$A:$Z,2,0),"")
... B123: =IFERROR(VLOOKUP(A123,'Field Map'!$A:$Z,2,0),"")

Sheet Schema Log
A1: Schema Log — version control, deprecation, and change approvals. Append one row per change event — never overwrite. Columns follow the 5-step evolution process. Steps 1–5 run left to right. | White = type Gold = select from list Blue = auto-filled
A2: Step 1 — Reference | C2: Step 2 — Gap check | D2: Step 3 — Change | F2: Step 4 — Version + status | I2: Step 5 — Impact + approval
A3: WCDM Leaf Path | B3: BDE Name | C3: Gap Check | D3: Change Type | E3: Change Notes | F3: Version | G3: Date | H3: Prior Status → New Status | I3: Source Mappings Affected | J3: Requirements Affected | K3: Consumer Delivery Impact | L3: Approved By | M3: Approval Date
A4: account.position.marketValue.amount | B4: =IFERROR(VLOOKUP(A4,'Field Map'!$A:$Z,2,0),"") -> Market Value | C4: Schema change required | D4: Add | E4: New leaf path. Datatype: decimal, Cardinality: 0..1. Reusable across equity and fixed income consumers. | F4: 1.0 | G4: 2026-01-10 | H4: N/A → Active | I4: Bloomberg and Calypso source mappings to be added to Source Map sheet. | J4: BR-001 (Risk Analytics P&L), BR-002 (Front Office valuation). | K4: Risk Analytics feed and Front Office dashboard cannot be delivered until source mappings are complete. | L4: J. Smith | M4: 2026-01-10
A5: account.position.marketValue.amount | B5: =IFERROR(VLOOKUP(A5,'Field Map'!$A:$Z,2,0),"") -> Market Value | C5: Need met by existing path or mapping | D5: Add | E5: Onboarding Calypso as a second source. Schema unchanged. Precedence rule added to Source Map: Bloomberg takes priority. | F5: 1.0 | G5: 2026-01-10 | H5: Active → Active | I5: Calypso row added to Source Map. | J5: No requirement impact. | K5: Calypso-sourced consumers may be added in a future iteration. | L5: J. Smith | M5: 2026-01-10
A6: account.position.marketValue.amount | B6: =IFERROR(VLOOKUP(A6,'Field Map'!$A:$Z,2,0),"") -> Market Value | C6: Schema change required | D6: Deprecate | E6: Replaced by account.position.marketValue.reportingCurrency.amount for multi-currency support. Both paths coexist until all consumers migrate. | F6: 1.1 | G6: 2026-06-01 | H6: Active → Deprecated | I6: Bloomberg and Calypso mappings must be replicated on the replacement path. | J6: BR-001, BR-002, BR-003 — all consumers must update their path references. | K6: Risk Analytics and Front Office must migrate to replacement path by Q3 2026. | L6: J. Smith | M6: 2026-06-01
B7: =IFERROR(VLOOKUP(A7,'Field Map'!$A:$Z,2,0),"")
B8: =IFERROR(VLOOKUP(A8,'Field Map'!$A:$Z,2,0),"")
B9: =IFERROR(VLOOKUP(A9,'Field Map'!$A:$Z,2,0),"")
B10: =IFERROR(VLOOKUP(A10,'Field Map'!$A:$Z,2,0),"")
B11: =IFERROR(VLOOKUP(A11,'Field Map'!$A:$Z,2,0),"")
B12: =IFERROR(VLOOKUP(A12,'Field Map'!$A:$Z,2,0),"")
B13: =IFERROR(VLOOKUP(A13,'Field Map'!$A:$Z,2,0),"")
B14: =IFERROR(VLOOKUP(A14,'Field Map'!$A:$Z,2,0),"")
B15: =IFERROR(VLOOKUP(A15,'Field Map'!$A:$Z,2,0),"")
B16: =IFERROR(VLOOKUP(A16,'Field Map'!$A:$Z,2,0),"")
B17: =IFERROR(VLOOKUP(A17,'Field Map'!$A:$Z,2,0),"")
B18: =IFERROR(VLOOKUP(A18,'Field Map'!$A:$Z,2,0),"")
... B123: =IFERROR(VLOOKUP(A123,'Field Map'!$A:$Z,2,0),"")
